brainf_interpret/__init__.py
brainf_interpret-1.1.0.dist-info/LICENSE
brainf_interpret-1.1.0.dist-info/METADATA
brainf_interpret-1.1.0.dist-info/WHEEL
brainf_interpret-1.1.0.dist-info/top_level.txt
brainf_interpret-1.1.0.dist-info/RECORD
